valorantstore/ValorantStore.py
valorantstore/ValorantStoreException.py
valorantstore/__init__.py
valorantstore-6.0.0.0.dist-info/LICENSE
valorantstore-6.0.0.0.dist-info/METADATA
valorantstore-6.0.0.0.dist-info/WHEEL
valorantstore-6.0.0.0.dist-info/top_level.txt
valorantstore-6.0.0.0.dist-info/RECORD
