Metadata-Version: 2.1
Name: valorantstore
Version: 6.0.0.0
Summary: Python module to display your Valorant store
Home-page: https://github.com/mahelbir/valorant-store
Author: Mahmuthan Elbir
Author-email: me@mahmuthanelbir.com.tr
License: MIT
Keywords: valorant store,valorant api
Classifier: Programming Language :: Python :: 3
Classifier: License :: OSI Approved :: MIT License
Classifier: Operating System :: OS Independent
Requires-Python: >=3.7
License-File: LICENSE
Requires-Dist: requests ~=2.28.2
Requires-Dist: cfscrape ~=2.1.1
